{
  "timestamp": "2025-07-18T18:23:59.247409",
  "project_root": "/Users/ved/Apps/lexicon",
  "steps": {
    "environment_validation": {
      "success": true,
      "timestamp": "2025-07-18T18:24:30.685910"
    },
    "configuration_validation": {
      "success": true,
      "timestamp": "2025-07-18T18:24:30.872324"
    },
    "security_setup": {
      "success": true,
      "timestamp": "2025-07-18T18:24:31.077618"
    },
    "performance_optimization": {
      "success": true,
      "timestamp": "2025-07-18T18:24:31.106192"
    },
    "health_checks": {
      "success": true,
      "timestamp": "2025-07-18T18:24:31.129576"
    }
  },
  "success": true,
  "errors": [],
  "warnings": [
    "Dependency check failed"
  ]
}